modeling/AutoHyperTuner.py
modeling/__init__.py
modeling/cant_use_.py
modeling/cant_use_ml.py
modeling/fix_bug_.py
modeling/fix_bug_ml.py
modeling/sandbox1_.py
modeling/utils_ml.py
modeling_tool/AutoHyperTuner.py
modeling_tool/__init__.py
modeling_tool/advanced_feature_engineering.py
modeling_tool/basic_feature_engineering.py
modeling_tool/cant_use_.py
modeling_tool/cant_use_ml.py
modeling_tool/dataprep.py
modeling_tool/fix_bug_.py
modeling_tool/fix_bug_ml.py
modeling_tool/lib01_xgb.py
modeling_tool/sandbox1_.py
modeling_tool/utils_ml.py
modeling_tool-0.1.3.dist-info/METADATA
modeling_tool-0.1.3.dist-info/WHEEL
modeling_tool-0.1.3.dist-info/top_level.txt
modeling_tool-0.1.3.dist-info/RECORD
